backend/api/__init__.py
backend/api/chat_history.py
backend/batch/__init__.py
backend/batch/utilities/__init__.py
backend/batch/utilities/chat_history/auth_utils.py
backend/batch/utilities/chat_history/cosmosdb.py
backend/batch/utilities/chat_history/database_client_base.py
backend/batch/utilities/chat_history/database_factory.py
backend/batch/utilities/chat_history/postgresdbservice.py
backend/batch/utilities/chat_history/sample_user.py
backend/batch/utilities/common/__init__.py
backend/batch/utilities/common/answer.py
backend/batch/utilities/common/source_document.py
backend/batch/utilities/document_chunking/__init__.py
backend/batch/utilities/document_chunking/chunking_strategy.py
backend/batch/utilities/document_chunking/document_chunking_base.py
backend/batch/utilities/document_chunking/fixed_size_overlap.py
backend/batch/utilities/document_chunking/layout.py
backend/batch/utilities/document_chunking/page.py
backend/batch/utilities/document_chunking/paragraph.py
backend/batch/utilities/document_chunking/strategies.py
backend/batch/utilities/document_loading/__init__.py
backend/batch/utilities/document_loading/document_loading_base.py
backend/batch/utilities/document_loading/layout.py
backend/batch/utilities/document_loading/read.py
backend/batch/utilities/document_loading/strategies.py
backend/batch/utilities/document_loading/web.py
backend/batch/utilities/document_loading/word_document.py
backend/batch/utilities/helpers/__init__.py
backend/batch/utilities/helpers/azure_blob_storage_client.py
backend/batch/utilities/helpers/azure_computer_vision_client.py
backend/batch/utilities/helpers/azure_form_recognizer_helper.py
backend/batch/utilities/helpers/azure_postgres_helper.py
backend/batch/utilities/helpers/azure_search_helper.py
backend/batch/utilities/helpers/document_chunking_helper.py
backend/batch/utilities/helpers/document_loading_helper.py
backend/batch/utilities/helpers/env_helper.py
backend/batch/utilities/helpers/llm_helper.py
cwyod_base-0.0.2.dist-info/licenses/LICENSE
cwyod_base-0.0.2.dist-info/METADATA
cwyod_base-0.0.2.dist-info/WHEEL
cwyod_base-0.0.2.dist-info/top_level.txt
cwyod_base-0.0.2.dist-info/RECORD
