Metadata-Version: 2.4
Name: cwyod-base
Version: 0.0.2
Summary: Add your description here
Author-email: Patrik <patrikhartl@gmail.com>
Classifier: Programming Language :: Python :: 3.11
Classifier: Operating System :: OS Independent
Requires-Python: ==3.11.11
License-File: LICENSE
Requires-Dist: azure-monitor-opentelemetry<2.0.0,>=1.6.4
Requires-Dist: opentelemetry-instrumentation-httpx<0.52,>=0.51b0
Requires-Dist: openai<2.0.0,>=1.63.0
Requires-Dist: flask<4.0.0,>=3.1.0
Requires-Dist: azure-mgmt-cognitiveservices<14.0.0,>=13.6.0
Requires-Dist: azure-identity<2.0.0,>=1.20.0
Requires-Dist: azure-cosmos<5.0.0,>=4.9.0
Requires-Dist: asyncpg<0.31.0,>=0.30.0
Requires-Dist: langchain<0.4.0,>=0.3.18
Requires-Dist: azure-storage-queue<13.0.0,>=12.12.0
Requires-Dist: chardet<6.0.0,>=5.2.0
Requires-Dist: azure-ai-formrecognizer<4.0.0,>=3.3.3
Requires-Dist: langchain-chroma<0.3.0,>=0.2.2
Requires-Dist: langchain-openai<0.4.0,>=0.3.5
Requires-Dist: langchain-community<0.4.0,>=0.3.17
Requires-Dist: azure-search<2.0.0,>=1.0.0b2
Requires-Dist: azure-search-documents==11.6.0b4
Requires-Dist: azure-functions<2.0.0,>=1.21.3
Requires-Dist: azure-ai-ml<2.0.0,>=1.25.0
Requires-Dist: python-docx<2.0.0,>=1.1.2
Requires-Dist: azure-ai-contentsafety<2.0.0,>=1.0.0
Requires-Dist: httpx<0.29.0,>=0.28.1
Requires-Dist: semantic-kernel<2.0.0,>=1.21.2
Requires-Dist: requests<3.0.0,>=2.32.3
Requires-Dist: azure-cognitiveservices-speech<2.0.0,>=1.42.0
Requires-Dist: azure-keyvault-secrets<5.0.0,>=4.9.0
Requires-Dist: psycopg==3.2.4
Requires-Dist: psycopg2-binary==2.9.10
Requires-Dist: azure-storage-blob==12.20.0
Requires-Dist: beautifulsoup4==4.13.3
Requires-Dist: azure-ai-inference==1.0.0b9
Dynamic: license-file
